{
"meta":{"test_sets":[],"test_metrics":[],"learn_metrics":[{"best_value":"Min","name":"RMSE"}],"launch_mode":"Train","parameters":"","iteration_count":100,"learn_sets":["learn"],"name":"experiment"},
"iterations":[
{"learn":[14.005006],"iteration":0,"passed_time":0.001355640619,"remaining_time":0.1342084213},
{"learn":[13.14441192],"iteration":1,"passed_time":0.00247605976,"remaining_time":0.1213269283},
{"learn":[12.34258257],"iteration":2,"passed_time":0.003601662833,"remaining_time":0.1164537649},
{"learn":[11.64527793],"iteration":3,"passed_time":0.004505548917,"remaining_time":0.108133174},
{"learn":[11.02766183],"iteration":4,"passed_time":0.005652705866,"remaining_time":0.1074014114},
{"learn":[10.43485794],"iteration":5,"passed_time":0.006794304187,"remaining_time":0.1064440989},
{"learn":[9.890641275],"iteration":6,"passed_time":0.007932702532,"remaining_time":0.1053916194},
{"learn":[9.492161212],"iteration":7,"passed_time":0.009077867028,"remaining_time":0.1043954708},
{"learn":[9.105082953],"iteration":8,"passed_time":0.01018274596,"remaining_time":0.1029588758},
{"learn":[8.674157135],"iteration":9,"passed_time":0.01127896209,"remaining_time":0.1015106588},
{"learn":[8.341743544],"iteration":10,"passed_time":0.01236844374,"remaining_time":0.1000719539},
{"learn":[8.049372916],"iteration":11,"passed_time":0.01354984941,"remaining_time":0.09936556233},
{"learn":[7.757318612],"iteration":12,"passed_time":0.01470287556,"remaining_time":0.09839616718},
{"learn":[7.522206899],"iteration":13,"passed_time":0.01588261479,"remaining_time":0.09756463371},
{"learn":[7.297756655],"iteration":14,"passed_time":0.01702962572,"remaining_time":0.09650121244},
{"learn":[7.088359431],"iteration":15,"passed_time":0.01811979419,"remaining_time":0.0951289195},
{"learn":[6.882113791],"iteration":16,"passed_time":0.0192693376,"remaining_time":0.09407970711},
{"learn":[6.704728832],"iteration":17,"passed_time":0.02042953473,"remaining_time":0.09306788042},
{"learn":[6.563881962],"iteration":18,"passed_time":0.02156399529,"remaining_time":0.09193071677},
{"learn":[6.418790279],"iteration":19,"passed_time":0.02267523787,"remaining_time":0.09070095148},
{"learn":[6.315756953],"iteration":20,"passed_time":0.02374144514,"remaining_time":0.08931305552},
{"learn":[6.210157751],"iteration":21,"passed_time":0.02483967381,"remaining_time":0.0880679344},
{"learn":[6.115058449],"iteration":22,"passed_time":0.02590440856,"remaining_time":0.08672345474},
{"learn":[6.014819884],"iteration":23,"passed_time":0.02696098577,"remaining_time":0.08537645493},
{"learn":[5.93117229],"iteration":24,"passed_time":0.02803569901,"remaining_time":0.08410709703},
{"learn":[5.844857622],"iteration":25,"passed_time":0.02913198081,"remaining_time":0.08291409922},
{"learn":[5.771145213],"iteration":26,"passed_time":0.03018793301,"remaining_time":0.08161922627},
{"learn":[5.704018229],"iteration":27,"passed_time":0.03124835837,"remaining_time":0.08035292153},
{"learn":[5.665806474],"iteration":28,"passed_time":0.03230584412,"remaining_time":0.07909361837},
{"learn":[5.616500369],"iteration":29,"passed_time":0.03336582913,"remaining_time":0.07785360129},
{"learn":[5.558023666],"iteration":30,"passed_time":0.03446112126,"remaining_time":0.07670378604},
{"learn":[5.510080976],"iteration":31,"passed_time":0.03583219316,"remaining_time":0.07614341046},
{"learn":[5.468747792],"iteration":32,"passed_time":0.03714269185,"remaining_time":0.07541091982},
{"learn":[5.429275534],"iteration":33,"passed_time":0.03827620757,"remaining_time":0.07430087351},
{"learn":[5.402117324],"iteration":34,"passed_time":0.03942692296,"remaining_time":0.07322142836},
{"learn":[5.367635151],"iteration":35,"passed_time":0.04054115538,"remaining_time":0.07207316512},
{"learn":[5.345181232],"iteration":36,"passed_time":0.04166735951,"remaining_time":0.07094712565},
{"learn":[5.319151269],"iteration":37,"passed_time":0.04279454326,"remaining_time":0.06982267584},
{"learn":[5.296134146],"iteration":38,"passed_time":0.04388240561,"remaining_time":0.06863658313},
{"learn":[5.269629003],"iteration":39,"passed_time":0.04498168883,"remaining_time":0.06747253325},
{"learn":[5.251147059],"iteration":40,"passed_time":0.04605712288,"remaining_time":0.06627732317},
{"learn":[5.248003302],"iteration":41,"passed_time":0.04651867976,"remaining_time":0.06424008157},
{"learn":[5.232376509],"iteration":42,"passed_time":0.04758254769,"remaining_time":0.06307453996},
{"learn":[5.213524255],"iteration":43,"passed_time":0.04869019165,"remaining_time":0.06196933482},
{"learn":[5.189691584],"iteration":44,"passed_time":0.04987004213,"remaining_time":0.06095227372},
{"learn":[5.166052198],"iteration":45,"passed_time":0.05096192647,"remaining_time":0.0598248702},
{"learn":[5.140406659],"iteration":46,"passed_time":0.05206602434,"remaining_time":0.05871275085},
{"learn":[5.118929684],"iteration":47,"passed_time":0.05316106385,"remaining_time":0.0575911525},
{"learn":[5.108792602],"iteration":48,"passed_time":0.05428936318,"remaining_time":0.05650525556},
{"learn":[5.098141225],"iteration":49,"passed_time":0.05536335098,"remaining_time":0.05536335098},
{"learn":[5.085926393],"iteration":50,"passed_time":0.05646995197,"remaining_time":0.05425544405},
{"learn":[5.067816804],"iteration":51,"passed_time":0.05752703753,"remaining_time":0.0531018808},
{"learn":[5.049834901],"iteration":52,"passed_time":0.05864818443,"remaining_time":0.05200876732},
{"learn":[5.03838627],"iteration":53,"passed_time":0.05961828037,"remaining_time":0.05078594254},
{"learn":[5.033534248],"iteration":54,"passed_time":0.06019631038,"remaining_time":0.04925152667},
{"learn":[5.023726885],"iteration":55,"passed_time":0.06106747975,"remaining_time":0.04798159123},
{"learn":[5.01290392],"iteration":56,"passed_time":0.06194420543,"remaining_time":0.04672983919},
{"learn":[5.005569127],"iteration":57,"passed_time":0.0628147807,"remaining_time":0.04548656533},
{"learn":[4.989969032],"iteration":58,"passed_time":0.06382201785,"remaining_time":0.04435089376},
{"learn":[4.976762446],"iteration":59,"passed_time":0.06471411841,"remaining_time":0.0431427456},
{"learn":[4.967222715],"iteration":60,"passed_time":0.06565477023,"remaining_time":0.04197600064},
{"learn":[4.954407599],"iteration":61,"passed_time":0.0665594088,"remaining_time":0.04079447636},
{"learn":[4.942125056],"iteration":62,"passed_time":0.06739310784,"remaining_time":0.03958007921},
{"learn":[4.930230716],"iteration":63,"passed_time":0.06837584222,"remaining_time":0.03846141125},
{"learn":[4.921695642],"iteration":64,"passed_time":0.06931513047,"remaining_time":0.03732353179},
{"learn":[4.906405625],"iteration":65,"passed_time":0.07018553886,"remaining_time":0.03615618669},
{"learn":[4.894330248],"iteration":66,"passed_time":0.07102946594,"remaining_time":0.03498466233},
{"learn":[4.88211557],"iteration":67,"passed_time":0.07194755491,"remaining_time":0.0338576729},
{"learn":[4.877946398],"iteration":68,"passed_time":0.07285167972,"remaining_time":0.0327304648},
{"learn":[4.863182126],"iteration":69,"passed_time":0.07371273618,"remaining_time":0.03159117265},
{"learn":[4.84646533],"iteration":70,"passed_time":0.07462646091,"remaining_time":0.03048123051},
{"learn":[4.838014752],"iteration":71,"passed_time":0.07552018773,"remaining_time":0.02936896189},
{"learn":[4.82981137],"iteration":72,"passed_time":0.07646306146,"remaining_time":0.02828085835},
{"learn":[4.817094767],"iteration":73,"passed_time":0.07745509215,"remaining_time":0.0272139513},
{"learn":[4.808314151],"iteration":74,"passed_time":0.07834191452,"remaining_time":0.02611397151},
{"learn":[4.796235023],"iteration":75,"passed_time":0.07929094099,"remaining_time":0.02503924452},
{"learn":[4.784434534],"iteration":76,"passed_time":0.08019009741,"remaining_time":0.02395288624},
{"learn":[4.774402487],"iteration":77,"passed_time":0.08105583794,"remaining_time":0.02286190301},
{"learn":[4.76731896],"iteration":78,"passed_time":0.08195552821,"remaining_time":0.02178564674},
{"learn":[4.75934113],"iteration":79,"passed_time":0.08284704703,"remaining_time":0.02071176176},
{"learn":[4.754106378],"iteration":80,"passed_time":0.083731836,"remaining_time":0.01964080104},
{"learn":[4.744002932],"iteration":81,"passed_time":0.08458205255,"remaining_time":0.01856679202},
{"learn":[4.731700554],"iteration":82,"passed_time":0.08554493502,"remaining_time":0.01752125175},
{"learn":[4.723284153],"iteration":83,"passed_time":0.08644888678,"remaining_time":0.01646645462},
{"learn":[4.712232782],"iteration":84,"passed_time":0.08731038591,"remaining_time":0.01540771516},
{"learn":[4.703046867],"iteration":85,"passed_time":0.08819891335,"remaining_time":0.01435796264},
{"learn":[4.698601855],"iteration":86,"passed_time":0.08912955964,"remaining_time":0.01331821006},
{"learn":[4.692429407],"iteration":87,"passed_time":0.0900628852,"remaining_time":0.01228130253},
{"learn":[4.675027364],"iteration":88,"passed_time":0.09099701501,"remaining_time":0.01124682208},
{"learn":[4.662368584],"iteration":89,"passed_time":0.09191453383,"remaining_time":0.01021272598},
{"learn":[4.646206172],"iteration":90,"passed_time":0.09282310554,"remaining_time":0.009180307141},
{"learn":[4.641245848],"iteration":91,"passed_time":0.09376800262,"remaining_time":0.008153739359},
{"learn":[4.633900435],"iteration":92,"passed_time":0.09474657364,"remaining_time":0.007131462532},
{"learn":[4.624738236],"iteration":93,"passed_time":0.09565038633,"remaining_time":0.006105343808},
{"learn":[4.612798287],"iteration":94,"passed_time":0.09661705592,"remaining_time":0.005085108207},
{"learn":[4.605222001],"iteration":95,"passed_time":0.09751925008,"remaining_time":0.004063302087},
{"learn":[4.601725912],"iteration":96,"passed_time":0.09834200802,"remaining_time":0.003041505403},
{"learn":[4.59722371],"iteration":97,"passed_time":0.09926580241,"remaining_time":0.002025832702},
{"learn":[4.580235665],"iteration":98,"passed_time":0.1001689121,"remaining_time":0.001011807193},
{"learn":[4.57591791],"iteration":99,"passed_time":0.1010701521,"remaining_time":0}
]}